mofh/__init__.py
mofh/errors.py
mofh/main.py
mofh/py.typed
mofh-1.0.2.dist-info/LICENSE.MD
mofh-1.0.2.dist-info/METADATA
mofh-1.0.2.dist-info/WHEEL
mofh-1.0.2.dist-info/top_level.txt
mofh-1.0.2.dist-info/RECORD
