Metadata-Version: 2.1
Name: mofh
Version: 1.0.2
Summary: API wrapper for https://myownfreehost.net
Home-page: https://github.com/Wallvon/mofh
Author: Robert S.
Author-email: admin@robert-s.dev
License: GPLv3
Keywords: mofh,myownfreehost,vistapanel,vpanel,byet,ifastnet,byethost,freehosting,free-hosting,api-wrapper,api,wrapper
Platform: unix
Platform: linux
Platform: osx
Platform: cygwin
Platform: win32
Platform: win64
Classifier: Programming Language :: Python :: 3
Classifier: Programming Language :: Python :: 3.8
Classifier: Programming Language :: Python :: 3.9
Classifier: Programming Language :: Python :: 3.10
Classifier: Operating System :: OS Independent
Requires-Python: >=3.8
License-File: LICENSE.MD
Requires-Dist: aiohttp[speedups] (>=3.8.1)
Requires-Dist: asyncio (>=3.4.3)
Requires-Dist: uvloop (>=0.16.0)
Requires-Dist: requests (>=2.28.1)
Requires-Dist: defusedxml (>=0.7.1)
Provides-Extra: testing
Requires-Dist: flake8 (==5.0.4) ; extra == 'testing'
Requires-Dist: tox (==3.25.1) ; extra == 'testing'
Requires-Dist: pytest (==7.1.2) ; extra == 'testing'
Requires-Dist: pytest-cov (==3.0.0) ; extra == 'testing'
Requires-Dist: pytest-asyncio (==0.19.0) ; extra == 'testing'
Requires-Dist: mypy (==0.971) ; extra == 'testing'
Requires-Dist: sphinx (==5.1.1) ; extra == 'testing'
